jaraco/__init__.py
jaraco/office/__init__.py
jaraco/office/convert.py
jaraco/office/excel.py
jaraco/office/grep.py
jaraco/office/word.py
jaraco.office-3.0.0.dist-info/LICENSE
jaraco.office-3.0.0.dist-info/METADATA
jaraco.office-3.0.0.dist-info/WHEEL
jaraco.office-3.0.0.dist-info/entry_points.txt
jaraco.office-3.0.0.dist-info/top_level.txt
jaraco.office-3.0.0.dist-info/RECORD
