Metadata-Version: 2.1
Name: jaraco.office
Version: 3.0.0
Summary: Utility library for working with MS Office documents
Home-page: https://github.com/jaraco/jaraco.office
Author: Jason R. Coombs
Author-email: jaraco@jaraco.com
License: UNKNOWN
Keywords: excel office word
Platform: UNKNOWN
Classifier: Development Status :: 5 - Production/Stable
Classifier: Intended Audience :: Developers
Classifier: License :: OSI Approved :: MIT License
Classifier: Programming Language :: Python :: 3
Classifier: Programming Language :: Python :: 3 :: Only
Classifier: Operating System :: Microsoft :: Windows
Requires-Python: >=3.6
Requires-Dist: jaraco.path
Provides-Extra: docs
Requires-Dist: sphinx ; extra == 'docs'
Requires-Dist: jaraco.packaging (>=3.2) ; extra == 'docs'
Requires-Dist: rst.linker (>=1.9) ; extra == 'docs'
Provides-Extra: testing
Requires-Dist: pytest (!=3.7.3,>=3.5) ; extra == 'testing'
Requires-Dist: pytest-checkdocs (>=1.2.3) ; extra == 'testing'
Requires-Dist: pytest-flake8 ; extra == 'testing'
Requires-Dist: pytest-cov ; extra == 'testing'
Requires-Dist: jaraco.test (>=3.2.0) ; extra == 'testing'
Requires-Dist: pytest-black (>=0.3.7) ; (platform_python_implementation != "PyPy") and extra == 'testing'
Requires-Dist: pytest-mypy ; (platform_python_implementation != "PyPy") and extra == 'testing'
Requires-Dist: pypiwin32 ; (platform_system == "Windows") and extra == 'testing'
